{
  "pipeline_id": "20250717_232652",
  "timestamp": "2025-07-17T23:28:14.824305",
  "model_type": "XGBoostOreGradePredictor",
  "model_path": "data\\models\\grade_model_20250717_232652.joblib",
  "scaler_path": "data\\models\\scaler_20250717_232652.joblib",
  "config": {
    "model_config": {
      "algorithm": "xgboost",
      "target_variable": "standardized_grade_ppm",
      "test_size": 0.2,
      "random_state": 42,
      "cv_folds": 5
    },
    "xgboost_params": {
      "objective": "reg:squarederror",
      "max_depth": 6,
      "learning_rate": 0.1,
      "n_estimators": 100,
      "subsample": 0.8,
      "colsample_bytree": 0.8,
      "random_state": 42
    },
    "feature_engineering": {
      "spatial_features": true,
      "geological_features": true,
      "statistical_features": true,
      "distance_features": true
    },
    "validation_metrics": {
      "primary": [
        "r2",
        "mae",
        "rmse"
      ],
      "secondary": [
        "mape",
        "explained_variance"
      ]
    },
    "data_sources": {
      "main_view": "vw_HoleSamples_ElementGrades",
      "elements": [
        "Cu",
        "Au",
        "Zn",
        "Pb",
        "Fe",
        "Ag"
      ],
      "datasets": [
        "Drilling_INF",
        "Drilling_BF",
        "Drilling_OP"
      ],
      "depth_columns": [
        "Depth_From",
        "Depth_To",
        "Interval_Length"
      ],
      "coordinate_columns": [
        "latitude",
        "longitude",
        "elevation"
      ]
    },
    "preprocessing": {
      "handle_missing": "median",
      "outlier_detection": "iqr",
      "scaling": "standard",
      "feature_selection": "correlation"
    }
  },
  "evaluation_results": {
    "model_name": "XGBoostOreGradePredictor_20250717_232652",
    "evaluation_timestamp": "2025-07-17T23:27:35.410439",
    "test_metrics": {
      "rmse": 616.070812367345,
      "r2_score": 0.912048856102694,
      "mae": 23.379728291101518,
      "mse": 379543.2458509604,
      "explained_variance": 0.9120634455178729,
      "mape": 9.945257520949273,
      "bias": 7.934669267807312,
      "relative_bias_percent": 1.5099126179642406,
      "cutoff_100ppm_accuracy": 0.9915665729619217,
      "cutoff_500ppm_accuracy": 0.9992333248147202,
      "cutoff_1000ppm_accuracy": 0.9990629525513246,
      "cutoff_2000ppm_accuracy": 0.9982962773660448
    },
    "train_metrics": {
      "rmse": 50.19963263195754,
      "r2_score": 0.9994528085012467,
      "mae": 9.422058428505487,
      "mse": 2520.0031163834965,
      "explained_variance": 0.9994528129234806,
      "mape": 9.983751920896967,
      "bias": -0.1427091178695001,
      "relative_bias_percent": -0.02784825204769896,
      "cutoff_100ppm_accuracy": 0.9924395698008732,
      "cutoff_500ppm_accuracy": 0.9990416356085614,
      "cutoff_1000ppm_accuracy": 0.9995474390373762,
      "cutoff_2000ppm_accuracy": 0.99845596848046
    },
    "cv_metrics": {
      "neg_mean_squared_error_mean": -484378.54630100017,
      "neg_mean_squared_error_std": 545686.3299607285,
      "neg_mean_squared_error_scores": [
        -1042727.4195651547,
        -25445.718065274676,
        -69221.4875797571,
        -32210.74650089181,
        -1252287.3597939226
      ],
      "neg_mean_absolute_error_mean": -24.856306008361763,
      "neg_mean_absolute_error_std": 8.554061235342024,
      "neg_mean_absolute_error_scores": [
        -37.53992051556538,
        -16.61484177230313,
        -19.340206481543138,
        -18.11111162975976,
        -32.67544964263741
      ],
      "r2_mean": 0.9177799589242046,
      "r2_std": 0.08720460980505479,
      "r2_scores": [
        0.7903296370674947,
        0.9910512683719684,
        0.980963775945238,
        0.9919484296916563,
        0.8346066835446657
      ],
      "rmse_mean": 695.9730930869383,
      "rmse_std": 545686.3299607285,
      "mae_mean": 24.856306008361763,
      "mae_std": 8.554061235342024
    },
    "feature_importance": [
      0.0006851995131000876,
      0.008949828334152699,
      0.0005460598622448742,
      0.001122278394177556,
      0.000692250207066536,
      0.0026589930057525635,
      0.00016727077309042215,
      0.001424848916940391,
      0.0018211000133305788,
      0.000300246145343408,
      0.09328997880220413,
      0.002607018919661641,
      9.377358219353482e-05,
      0.000494546489790082,
      0.0006594921578653157,
      0.19238482415676117,
      0.0841476246714592,
      0.003811229718849063,
      0.052603986114263535,
      0.0001285719044972211,
      0.0004141922399867326,
      0.0007467613904736936,
      0.03376949951052666,
      0.007402489427477121,
      0.002764250384643674,
      0.0,
      0.0,
      0.0,
      0.0,
      0.0,
      0.0,
      0.0,
      0.000198950816411525,
      0.0029788005631417036,
      0.0001849151885835454,
      4.538390567176975e-05,
      0.00032748133526183665,
      0.0031398767605423927,
      0.0007709254859946668,
      0.013705318793654442,
      0.0008009540033526719,
      0.027799032628536224,
      0.0005534625379368663,
      0.004771915264427662,
      0.000414199021179229,
      0.0005692089325748384,
      0.000389323802664876,
      0.26971539855003357,
      0.02833520993590355,
      0.0,
      0.00030226079979911447,
      0.0,
      0.005463456269353628,
      0.13059358298778534,
      0.0,
      0.0,
      0.0,
      0.0003197593323420733,
      0.014934311620891094
    ]
  },
  "feature_names": [
    "latitude",
    "longitude",
    "elevation",
    "mid_depth",
    "Interval_Length",
    "grade_tonnage",
    "lat_lon_ratio",
    "distance_from_center",
    "depth_ratio",
    "interval_ratio",
    "log_grade",
    "grade_per_meter",
    "element_encoded",
    "dataset_encoded",
    "labcode_encoded",
    "sample_mean",
    "sample_std",
    "sample_min",
    "sample_max",
    "sample_count",
    "hole_mean",
    "hole_std",
    "hole_min",
    "hole_max",
    "hole_count",
    "element_mean",
    "element_std",
    "element_count",
    "dataset_mean",
    "dataset_std",
    "dataset_count",
    "depth_normalized",
    "elevation_normalized",
    "Depth_From",
    "Depth_To",
    "lat_norm",
    "lon_norm",
    "distance_to_center",
    "angle_from_center",
    "quadrant",
    "grade_rolling_mean",
    "grade_rolling_std",
    "grade_rolling_median",
    "local_coefficient_variation",
    "grade_rolling_q25",
    "grade_rolling_q75",
    "local_iqr",
    "grade_log",
    "grade_sqrt",
    "grade_squared",
    "grade_category",
    "grade_category_encoded",
    "is_anomaly",
    "anomaly_score",
    "avg_neighbor_distance",
    "min_neighbor_distance",
    "max_neighbor_distance",
    "avg_neighbor_grade",
    "grade_vs_neighbors"
  ]
}